rnapolis/adapter.py
rnapolis/adapters/__init__.py
rnapolis/adapters/barnaba.py
rnapolis/adapters/bpnet.py
rnapolis/adapters/dnatco.py
rnapolis/adapters/dssr.py
rnapolis/adapters/fr3d.py
rnapolis/adapters/maxit.py
rnapolis/adapters/mc_annotate.py
rnapolis/adapters/rnaview.py
rnapolis/aligner.py
rnapolis/annotator.py
rnapolis/clashfinder.py
rnapolis/common.py
rnapolis/component_A.csv
rnapolis/component_C.csv
rnapolis/component_G.csv
rnapolis/component_U.csv
rnapolis/default_config.ini
rnapolis/distiller.py
rnapolis/geometry.py
rnapolis/metareader.py
rnapolis/mmcif_pdbx_v50.dic
rnapolis/molecule_filter.py
rnapolis/motif_extractor.py
rnapolis/parser.py
rnapolis/parser_v2.py
rnapolis/py.typed
rnapolis/rfam_folder.py
rnapolis/splitter.py
rnapolis/tertiary.py
rnapolis/tertiary_v2.py
rnapolis/transformer.py
rnapolis/unifier.py
rnapolis/util.py
rnapolis-0.13.0.dist-info/METADATA
rnapolis-0.13.0.dist-info/WHEEL
rnapolis-0.13.0.dist-info/entry_points.txt
rnapolis-0.13.0.dist-info/licenses/LICENSE
rnapolis-0.13.0.dist-info/RECORD
