Metadata-Version: 2.4
Name: RNApolis
Version: 0.13.0
Summary: A Python library containing RNA-related bioinformatics functions and classes
License-File: LICENSE
Author: Tomasz Zok
Author-email: tomasz.zok@cs.put.poznan.pl
Requires-Python: >=3.12,<4.0
Classifier: Development Status :: 5 - Production/Stable
Classifier: Environment :: Console
Classifier: Intended Audience :: Science/Research
Classifier: License :: OSI Approved :: MIT License
Classifier: Operating System :: OS Independent
Classifier: Programming Language :: Python :: 3
Classifier: Programming Language :: Python :: 3.12
Classifier: Programming Language :: Python :: 3.13
Classifier: Programming Language :: Python :: 3.14
Classifier: Topic :: Scientific/Engineering :: Bio-Informatics
Requires-Dist: appdirs
Requires-Dist: faiss-cpu
Requires-Dist: graphviz
Requires-Dist: mmcif
Requires-Dist: numpy
Requires-Dist: ordered-set
Requires-Dist: orjson
Requires-Dist: pandas
Requires-Dist: pulp
Requires-Dist: requests
Requires-Dist: scikit-learn
Requires-Dist: scipy
Requires-Dist: shapely
Requires-Dist: tqdm
Requires-Dist: viennarna
Project-URL: Homepage, https://github.com/tzok/rnapolis-py
Project-URL: Repository, https://github.com/tzok/rnapolis-py
